spongeblob/__init__.py
spongeblob/retriable_storage.py
spongeblob/storage/__init__.py
spongeblob/storage/s3.py
spongeblob/storage/storage.py
spongeblob/storage/wabs.py
spongeblob-0.1.1.dist-info/METADATA
spongeblob-0.1.1.dist-info/RECORD
spongeblob-0.1.1.dist-info/WHEEL
spongeblob-0.1.1.dist-info/top_level.txt
