Metadata-Version: 2.1
Name: spongeblob
Version: 0.1.1
Summary: Spongeblob: A wrapper library for various cloud storage
Home-page: https://github.com/helpshift/spongeblob.py
License: MIT License
Platform: UNKNOWN
Requires-Dist: azure-storage-blob (==1.1.0)
Requires-Dist: boto3 (==1.7.12)
Requires-Dist: tenacity (==4.10.0)
